README.rst
setup.py
asciitree/__init__.py
asciitree/drawing.py
asciitree/traversal.py
asciitree/util.py
asciitree.egg-info/PKG-INFO
asciitree.egg-info/SOURCES.txt
asciitree.egg-info/dependency_links.txt
asciitree.egg-info/top_level.txt