Metadata-Version: 1.0
Name: asciitree
Version: 0.3
Summary: Draws ASCII trees.
Home-page: http://github.com/mbr/asciitree
Author: Marc Brinkmann
Author-email: git@marcbrinkmann.de
License: MIT
Platform: UNKNOWN
